setup.py
nose_tags.egg-info/PKG-INFO
nose_tags.egg-info/SOURCES.txt
nose_tags.egg-info/dependency_links.txt
nose_tags.egg-info/entry_points.txt
nose_tags.egg-info/requires.txt
nose_tags.egg-info/top_level.txt
tag/__init__.py
tag/plugin.py