Metadata-Version: 1.1
Name: nose-tags
Version: 0.2.1
Summary: A better nose attrib plugin.
Home-page: https://github.com/travispavek/nose-tags
Author: Travis Pavek
Author-email: travis.pavek@gmail.com
License: UNKNOWN
Download-URL: https://github.com/travispavek/nose-tags/tarball/v0.2.1
Keywords: nose,attrib,attribute,select,exclude,tag,collect
Platform: UNKNOWN
Classifier: Programming Language :: Python :: 2
Classifier: Programming Language :: Python :: 3
Classifier: Topic :: Software Development :: Testing
